openTSNE/__init__.py
openTSNE/_tsne.cpython-310-x86_64-linux-gnu.so
openTSNE/_tsne.pxd
openTSNE/_tsne.pyx
openTSNE/affinity.py
openTSNE/callbacks.py
openTSNE/inference_io.py
openTSNE/initialization.py
openTSNE/kl_divergence.cpython-310-x86_64-linux-gnu.so
openTSNE/kl_divergence.pyx
openTSNE/light_csr.py
openTSNE/metrics.py
openTSNE/nearest_neighbors.py
openTSNE/quad_tree.cpython-310-x86_64-linux-gnu.so
openTSNE/quad_tree.pxd
openTSNE/quad_tree.pyx
openTSNE/sklearn.py
openTSNE/tsne.py
openTSNE/utils.py
openTSNE/version.py
openTSNE/_matrix_mul/__init__.py
openTSNE/_matrix_mul/matrix_mul.cpython-310-x86_64-linux-gnu.so
openTSNE/_matrix_mul/matrix_mul.pxd
openTSNE/_matrix_mul/matrix_mul_fftw3.pyx
openTSNE/_matrix_mul/matrix_mul_numpy.pyx
openTSNE/dependencies/__init__.py
openTSNE/dependencies/annoy/__init__.py
openTSNE/dependencies/annoy/annoylib.cpython-310-x86_64-linux-gnu.so
openTSNE/dependencies/annoy/annoylib.h
openTSNE/dependencies/annoy/annoymodule.cc
openTSNE/dependencies/annoy/kissrandom.h
openTSNE/dependencies/annoy/mman.h
opentsneslim.libs/libgomp-a34b3233.so.1.0.0
opentsneslim-1.0.4.dist-info/METADATA
opentsneslim-1.0.4.dist-info/WHEEL
opentsneslim-1.0.4.dist-info/top_level.txt
opentsneslim-1.0.4.dist-info/RECORD
opentsneslim-1.0.4.dist-info/licenses/LICENSE
