Metadata-Version: 2.4
Name: openTSNEslim
Version: 1.0.4
Summary: openTSNEslim is a slimmed down version of openTSNE that doesn't require use of scikit-learn or scipy for inference. This is useful for creating a smaller bundle for deployment.
Home-page: https://github.com/engagesmarter/openTSNEslim
Author: Sam Pink
Author-email: Pavlin Poličar <pavlin.g.p@gmail.com>, Sam Pink <sam@engagesmarter.ai>
License-Expression: MIT
Project-URL: Homepage, https://github.com/engagesmarter/openTSNEslim
Classifier: Programming Language :: Python :: 3
Classifier: Operating System :: OS Independent
Requires-Python: >=3.9
License-File: LICENSE
Dynamic: author
Dynamic: home-page
Dynamic: license-file
Dynamic: requires-python
